jl95/net/rpc/__init__.py
jl95/net/rpc/util.py
jl95terceira_net_rpc-1.0.0.dist-info/METADATA
jl95terceira_net_rpc-1.0.0.dist-info/WHEEL
jl95terceira_net_rpc-1.0.0.dist-info/RECORD
