Metadata-Version: 2.4
Name: jl95terceira_net_rpc
Version: 1.0.0
Summary: Network Synchronous Request/Response
Project-URL: Homepage, https://github.com/jl95terceira/net-rpc-python
Project-URL: Issues, https://github.com/jl95terceira/net-rpc-python/issues
Author-email: Joao Luis Ornelas da Silva <jl95terceira@gmail.com>
Classifier: License :: OSI Approved :: MIT License
Classifier: Operating System :: OS Independent
Classifier: Programming Language :: Python :: 3
Requires-Python: >=3.12
Requires-Dist: jl95terceira-batteries>=1.7.1
Requires-Dist: jl95terceira-net-io>=1.5.0
